_fastseqio.cpython-310-darwin.so
fastseqio/__init__.py
fastseqio/fastseqio.py
fastseqio-0.1.10.dist-info/RECORD
fastseqio-0.1.10.dist-info/WHEEL
fastseqio-0.1.10.dist-info/top_level.txt
fastseqio-0.1.10.dist-info/METADATA
fastseqio-0.1.10.dist-info/licenses/LICENSE
