Metadata-Version: 2.4
Name: fastseqio
Version: 0.1.10
Summary: A package for reading and writing fasta/fastq files
Home-page: https://github.com/dwpeng/fastseqio
Author: dwpeng
Author-email: dwpeng <1732889554@qq.com>
License: The MIT License (MIT)
Project-URL: homepage, https://github.com/dwpeng/fastseqio
Project-URL: repository, https://github.com/dwpeng/fastseqio
Requires-Python: >=3.8
License-File: LICENSE
Dynamic: author
Dynamic: home-page
Dynamic: license-file
